protox_gatekeeper/__init__.py
protox_gatekeeper/core.py
protox_gatekeeper/geo.py
protox_gatekeeper/ops.py
protox_gatekeeper/session.py
protox_gatekeeper/verify.py
protox_gatekeeper-0.2.0.dist-info/licenses/LICENSE
protox_gatekeeper-0.2.0.dist-info/METADATA
protox_gatekeeper-0.2.0.dist-info/WHEEL
protox_gatekeeper-0.2.0.dist-info/top_level.txt
protox_gatekeeper-0.2.0.dist-info/RECORD
