Metadata-Version: 2.4
Name: protox-gatekeeper
Version: 0.2.0
Summary: Fail-closed Tor session enforcement for Python HTTP(S) traffic
Author: Tom Erik Harnes
License: MIT License
Project-URL: Homepage, https://github.com/ProtoXCode/protox-gatekeeper
Project-URL: Repository, https://github.com/ProtoXCode/protox-gatekeeper
Project-URL: Issues, https://github.com/ProtoXCode/protox-gatekeeper/issues
Keywords: tor,privacy,networking,security,proxy
Classifier: Programming Language :: Python :: 3
Classifier: Programming Language :: Python :: 3.10
Classifier: Programming Language :: Python :: 3.11
Classifier: Programming Language :: Python :: 3.12
Classifier: License :: OSI Approved :: MIT License
Classifier: Operating System :: OS Independent
Requires-Python: >=3.10
License-File: LICENSE
Requires-Dist: requests
Requires-Dist: pysocks
Dynamic: license-file
